mseep_mcp_server_llmling-1.0.0.dist-info/licenses/LICENSE
tests/__init__.py
tests/conftest.py
tests/test_events.py
tests/test_handshake.py
tests/test_injection_server.py
tests/test_mcp_protocol.py
tests/test_server_integration.py
tests/test_uri_handling.py
tests/test_zed_mode.py
mseep_mcp_server_llmling-1.0.0.dist-info/METADATA
mseep_mcp_server_llmling-1.0.0.dist-info/WHEEL
mseep_mcp_server_llmling-1.0.0.dist-info/top_level.txt
mseep_mcp_server_llmling-1.0.0.dist-info/RECORD
